{
  "resourceType": "MeasureReport",
  "id": "FEMAexampleDE-positiveIncreasePercent",
  "identifier": [
    {
      "system": "https://www.census.gov/geographies",
      "value": "10"
    }
  ],
  "status": "complete",
  "type": "summary",
  "measure": "http://ainq.com/fhir/us/saner/Measure/SANERpositiveIncreasePercent",
  "subject": {
    "extension": [
      {
        "url": "http://hl7.org/fhir/StructureDefinition/geolocation",
        "extension": [
          {
            "url": "latitude",
            "valueDecimal": 38.9896
          },
          {
            "url": "longitude",
            "valueDecimal": 75.505
          }
        ]
      }
    ],
    "reference": "Location/states-DE",
    "display": "State of Delaware"
  },
  "date": "2020-03-31",
  "reporter": {
    "reference": "Organization/DE-DPH",
    "display": "Delaware Department of Public Health"
  },
  "period": {
    "start": "2020-03-31",
    "end": "2020-03-31"
  },
  "group": [
    {
      "population": [
        {
          "code": {
            "coding": [
              {
                "code": "numerator",
                "system": "http://terminology.hl7.org/CodeSystem/measure-population"
              }
            ]
          },
          "count": 142
        },
        {
          "code": {
            "coding": [
              {
                "code": "denominator",
                "system": "http://terminology.hl7.org/CodeSystem/measure-population"
              }
            ]
          },
          "count": 1622
        }
      ],
      "measureScore": {
        "value": 8.75,
        "unit": "%",
        "code": "%"
      }
    }
  ]
}
